django_ninecms-0.6.0.dist-info/DESCRIPTION.rst
django_ninecms-0.6.0.dist-info/METADATA
django_ninecms-0.6.0.dist-info/RECORD
django_ninecms-0.6.0.dist-info/WHEEL
django_ninecms-0.6.0.dist-info/metadata.json
django_ninecms-0.6.0.dist-info/top_level.txt
ninecms/__init__.py
ninecms/__init__.pyc
ninecms/admin.py
ninecms/admin.pyc
ninecms/apps.py
ninecms/apps.pyc
ninecms/checks.py
ninecms/forms.py
ninecms/forms.pyc
ninecms/models.py
ninecms/models.pyc
ninecms/settings.py
ninecms/signals.py
ninecms/signals.pyc
ninecms/urls.py
ninecms/urls.pyc
ninecms/views.py
ninecms/views.pyc
ninecms/__pycache__/__init__.cpython-34.pyc
ninecms/__pycache__/admin.cpython-34.pyc
ninecms/__pycache__/apps.cpython-34.pyc
ninecms/__pycache__/checks.cpython-34.pyc
ninecms/__pycache__/forms.cpython-34.pyc
ninecms/__pycache__/models.cpython-34.pyc
ninecms/__pycache__/settings.cpython-34.pyc
ninecms/__pycache__/signals.cpython-34.pyc
ninecms/__pycache__/urls.cpython-34.pyc
ninecms/__pycache__/views.cpython-34.pyc
ninecms/locale/el/LC_MESSAGES/django.po
ninecms/management/__init__.py
ninecms/management/__pycache__/__init__.cpython-34.pyc
ninecms/management/commands/__init__.py
ninecms/management/commands/cache_clear.py
ninecms/management/commands/check_updates.py
ninecms/management/commands/__pycache__/__init__.cpython-34.pyc
ninecms/management/commands/__pycache__/cache_clear.cpython-34.pyc
ninecms/management/commands/__pycache__/check_updates.cpython-34.pyc
ninecms/migrations/0001_squashed_0024_auto_20150416_1551.py
ninecms/migrations/0002_auto_20150519_1102.py
ninecms/migrations/0003_auto_20150623_1731.py
ninecms/migrations/0004_auto_20150624_1131.py
ninecms/migrations/0005_auto_20150624_1841.py
ninecms/migrations/0006_auto_20150701_1401.py
ninecms/migrations/0007_auto_20150727_1833.py
ninecms/migrations/0008_auto_20150819_1516.py
ninecms/migrations/0009_auto_20150924_1456.py
ninecms/migrations/0010_auto_20150924_1850.py
ninecms/migrations/0011_auto_20151202_1400.py
ninecms/migrations/0012_auto_20151218_1637.py
ninecms/migrations/0013_auto_20160117_1209.py
ninecms/migrations/__init__.py
ninecms/migrations/__init__.pyc
