Metadata-Version: 2.0
Name: django-ninecms
Version: 0.6.0
Summary: Nine CMS is a Django app to manage content.
Home-page: https://github.com/Wtower/django-ninecms/
Author: George Karakostas
Author-email: info@9-dev.com
License: BSD-3 License
Keywords: cms content management system
Platform: UNKNOWN
Classifier: Environment :: Web Environment
Classifier: Framework :: Django
Classifier: Intended Audience :: Developers
Classifier: License :: OSI Approved :: BSD License
Classifier: Operating System :: OS Independent
Classifier: Programming Language :: Python
Classifier: Programming Language :: Python :: 3
Classifier: Programming Language :: Python :: 3.4
Classifier: Programming Language :: Python :: 3.5
Classifier: Topic :: Internet :: WWW/HTTP
Classifier: Topic :: Internet :: WWW/HTTP :: Dynamic Content
Requires-Dist: Django
Requires-Dist: Pillow
Requires-Dist: bleach
Requires-Dist: django-guardian
Requires-Dist: django-mptt
Requires-Dist: pytz
